kelctl/__init__.py
kelctl/kelctl.py
kelctl/kelenums.py
kelctl/kelerrors.py
kelctl/kellists.py
py_kelctl-0.3.1.dist-info/LICENSE
py_kelctl-0.3.1.dist-info/METADATA
py_kelctl-0.3.1.dist-info/WHEEL
py_kelctl-0.3.1.dist-info/top_level.txt
py_kelctl-0.3.1.dist-info/RECORD
