Metadata-Version: 2.1
Name: py_kelctl
Version: 0.3.1
Summary: A library for controlling the KEL103 electronic load
Project-URL: Homepage, https://github.com/vorbeiei/kelctl
Project-URL: Bug Reports, https://github.com/vorbeiei/kelctl/issues
Project-URL: Source, https://github.com/vorbeiei/kelctl
Keywords: KEL103,library,development
Classifier: Development Status :: 4 - Beta
Classifier: Intended Audience :: Developers
Classifier: Topic :: Software Development :: Libraries
Classifier: License :: OSI Approved :: MIT License
Classifier: Programming Language :: Python :: 3
Classifier: Programming Language :: Python :: 3.10
Classifier: Programming Language :: Python :: 3.11
Classifier: Programming Language :: Python :: 3.12
Classifier: Programming Language :: Python :: 3.13
Classifier: Programming Language :: Python :: 3 :: Only
Requires-Python: >=3.10
License-File: LICENSE
Requires-Dist: aenum
